rest_endpoints/__init__.py
rest_endpoints/api.py
rest_endpoints/credentials.py
rest_endpoints/exceptions.py
rest_endpoints/methods.py
rest_endpoints-0.1.0.dist-info/LICENSE
rest_endpoints-0.1.0.dist-info/METADATA
rest_endpoints-0.1.0.dist-info/WHEEL
rest_endpoints-0.1.0.dist-info/RECORD
