Metadata-Version: 2.1
Name: rest-endpoints
Version: 0.1.0
Summary: library to help mapping ReST API endpoints
License: MIT
Author: Ramon Moraes
Author-email: nocfg@proton.me
Requires-Python: >=3.8.1,<4.0.0
Classifier: License :: OSI Approved :: MIT License
Classifier: Programming Language :: Python :: 3
Classifier: Programming Language :: Python :: 3.9
Classifier: Programming Language :: Python :: 3.10
Classifier: Programming Language :: Python :: 3.11
Classifier: Programming Language :: Python :: 3.12
Classifier: Programming Language :: Python :: 3.13
Requires-Dist: requests (>=2.32.3,<3.0.0)
